security_utils/CountryFirewall.py
security_utils/DinamicBlockedIPList.py
security_utils/SQLInjection.py
security_utils/__init__.py
security_utils/flask_security_utils.py
Flask_Security_Utils-1.0.2.dist-info/METADATA
Flask_Security_Utils-1.0.2.dist-info/WHEEL
Flask_Security_Utils-1.0.2.dist-info/top_level.txt
Flask_Security_Utils-1.0.2.dist-info/RECORD
