Metadata-Version: 2.1
Name: Flask-Security-Utils
Version: 1.0.2
Summary: Library for flask security enhancement, Geo IP blocking and retro-compatibility.
Home-page: https://github.com/alejivo/Flask-Security-Utils
Author: Alejivo (Alejandro Javier Moyano)
Author-email: email@alejivo.com
License: BSD 3-Clause License
Project-URL: Bug Tracker, https://github.com/alejivo/Flask-Security-Utils/issues
Platform: UNKNOWN
Classifier: Programming Language :: Python :: 3
Classifier: License :: OSI Approved :: BSD License
Classifier: Operating System :: OS Independent
Classifier: Framework :: Flask
Classifier: Topic :: Security
Classifier: Topic :: System :: Networking :: Firewalls
Requires-Dist: Flask (>=1.1.4)
Requires-Dist: IP2Location (<=8.7.4)
